dashuta/__init__.py
dashuta/version.py
dashuta-0.0.1.dist-info/LICENSE
dashuta-0.0.1.dist-info/METADATA
dashuta-0.0.1.dist-info/WHEEL
dashuta-0.0.1.dist-info/top_level.txt
dashuta-0.0.1.dist-info/RECORD
