Metadata-Version: 2.2
Name: dashuta
Version: 0.0.1
Summary: DASHUTA: - Unified Trading Assistant
Home-page: http://github.com/atomicai/dashuta
Download-URL: https://github.com/atomicai/dashuta/archive/0.0.1.tar.gz
Author: Igor Tarlinskiy
Author-email: Igor Tarlinskiy <itarlinskiy@gmail.com>, Eldar Khayarov <eldarhacks@gmail.com>
Maintainer: Eldar Khayarov
Maintainer-email: eldarhacks@gmail.com
License: MIT License
Project-URL: Home, https://github.com/atomicai/dashuta
Project-URL: Source, https://github.com/atomicai/dashuta
Project-URL: Tracker, https://github.com/atomicai/dashuta/issues
Classifier: Programming Language :: Python :: 3
Classifier: License :: OSI Approved :: MIT License
Classifier: Operating System :: OS Independent
Requires-Python: >=3.7
License-File: LICENSE
Dynamic: author
Dynamic: description
Dynamic: description-content-type
Dynamic: download-url
Dynamic: home-page
Dynamic: maintainer
Dynamic: maintainer-email
Dynamic: summary
